{"911249290851127297": {"users": {"761159873194491915": {"level": 0, "xp": 260, "username": "Osama cool#1017"}, "909763638406025226": {"level": 0, "xp": 200, "username": "Toadster#1171"}, "343897817678479361": {"level": 0, "xp": 445, "username": "Flambe#3497"}, "255511295019712512": {"level": 0, "xp": 0, "username": "Zack Horsch#4887"}, "541732474078756869": {"level": 0, "xp": 0, "username": "The Chosen#9571"}, "689437167667380227": {"level": 0, "xp": 0, "username": "chugjugwithme#3012"}, "314074948710957056": {"level": 0, "xp": 125, "username": "Thymen2203#5554"}, "437808476106784770": {"level": 0, "xp": 65, "username": "Arcane#7800"}, "755847014977110067": {"level": 0, "xp": 20, "username": "GazTheTaz6385#5542"}, "251194627330146305": {"level": 0, "xp": 0, "username": "Doggoception#5625"}, "559512846858321920": {"level": 0, "xp": 70, "username": "thygroovyone#0876"}, "900090447492448256": {"level": 0, "xp": 0, "username": "MrAsianPie#6611"}, "692856643192488076": {"level": 0, "xp": 0, "username": "AmericanDude\ud83c\uddfa\ud83c\uddf8x\ud83c\uddf7\ud83c\uddfa#4146"}, "710744437965455431": {"level": 0, "xp": 5, "username": "Obi Wan Kenobi#9803"}, "769321240732893184": {"level": 0, "xp": 25, "username": "The_Dark_Luis55\ud83c\udde9\ud83c\uddea\ud83c\uddf3\ud83c\uddf1#4809"}}}, "909762686030589972": {"users": {"761159873194491915": {"level": 0, "xp": 15, "username": "Osama cool#1017"}, "909763638406025226": {"level": 0, "xp": 0, "username": "Toadster#1171"}, "770174479598485535": {"level": 0, "xp": 35, "username": "Hassan#0003"}, "343897817678479361": {"level": 0, "xp": 0, "username": "Flambe#3497"}}}}